<keyframes>
    <key>
        <px>-74.217567444</px>
        <py>43.861610413</py>
        <pz>-227.154602051</pz>
        <ox>0.201342732</ox>
        <oy>-0.962805271</oy>
        <oz>-0.121615246</oz>
        <ow>0.133217424</ow>
        <easein>0</easein>
        <easeout>0</easeout>
        <time>00:00:00:082</time>
        <value>0.800000012</value>
    </key>
    <key>
        <px>-97.996887207</px>
        <py>51.936630249</py>
        <pz>-282.364624023</pz>
        <ox>0.201342568</ox>
        <oy>-0.962805212</oy>
        <oz>-0.121615238</oz>
        <ow>0.133217305</ow>
        <easein>0</easein>
        <easeout>0</easeout>
        <time>00:00:19:602</time>
        <value>1.000000000</value>
    </key>
    <key>
        <px>-105.356987000</px>
        <py>62.263954163</py>
        <pz>-322.458801270</pz>
        <ox>0.201342732</ox>
        <oy>-0.962805271</oy>
        <oz>-0.121615246</oz>
        <ow>0.133217424</ow>
        <easein>0</easein>
        <easeout>0</easeout>
        <time>00:00:37:580</time>
        <value>0.800000012</value>
    </key>
    <key>
        <px>20.972515106</px>
        <py>82.265060425</py>
        <pz>-214.009994507</pz>
        <ox>0.184741557</ox>
        <oy>-0.972917736</oy>
        <oz>-0.138915181</oz>
        <ow>0.008607915</ow>
        <easein>0</easein>
        <easeout>0</easeout>
        <time>00:01:08:489</time>
        <value>0.800000012</value>
    </key>
    <key>
        <px>-74.217567444</px>
        <py>43.861610413</py>
        <pz>-227.154602051</pz>
        <ox>0.201342732</ox>
        <oy>-0.962805271</oy>
        <oz>-0.121615246</oz>
        <ow>0.133217424</ow>
        <easein>0</easein>
        <easeout>0</easeout>
        <time>00:02:03:224</time>
        <value>0.500000000</value>
    </key>
</keyframes>
