<Canvas>
    <Kind>42</Kind>
    <Name>text</Name>
    <IsMinified>1</IsMinified>
    <XPosition>1.000000000</XPosition>
    <YPosition>47.000000000</YPosition>
</Canvas>
<Widget>
    <Kind>2</Kind>
    <Name>RENDER TEXT</Name>
    <Value>1</Value>
</Widget>
<Widget>
    <Kind>2</Kind>
    <Name>DRAW SPEAKER NAMES </Name>
    <Value>0</Value>
</Widget>
<Widget>
    <Kind>25</Kind>
    <Name>T HUE</Name>
    <Value>1.000000000</Value>
</Widget>
<Widget>
    <Kind>25</Kind>
    <Name>T SAT</Name>
    <Value>1.000000000</Value>
</Widget>
<Widget>
    <Kind>25</Kind>
    <Name>T BRI</Name>
    <Value>1.000000000</Value>
</Widget>
<Widget>
    <Kind>25</Kind>
    <Name>T ALPHA</Name>
    <Value>1.000000000</Value>
</Widget>
<Widget>
    <Kind>25</Kind>
    <Name>T HUE</Name>
    <Value>1.000000000</Value>
</Widget>
<Widget>
    <Kind>25</Kind>
    <Name>T SAT</Name>
    <Value>0.963350475</Value>
</Widget>
<Widget>
    <Kind>25</Kind>
    <Name>T BRI</Name>
    <Value>0.246072650</Value>
</Widget>
<Widget>
    <Kind>25</Kind>
    <Name>T ALPHA</Name>
    <Value>1.000000000</Value>
</Widget>
<Widget>
    <Kind>25</Kind>
    <Name>STRING WIDTH</Name>
    <Value>1054.660034180</Value>
</Widget>
<Widget>
    <Kind>25</Kind>
    <Name>SET SIZE</Name>
    <Value>40.453693390</Value>
</Widget>
