<Canvas>
    <Kind>42</Kind>
    <Name>transform</Name>
    <IsMinified>0</IsMinified>
    <XPosition>267.000000000</XPosition>
    <YPosition>19.000000000</YPosition>
</Canvas>
<Widget>
    <Kind>4</Kind>
    <Name>positionOffset.x</Name>
    <Value>4.926086426</Value>
</Widget>
<Widget>
    <Kind>4</Kind>
    <Name>positionOffset.y</Name>
    <Value>54.187133789</Value>
</Widget>
<Widget>
    <Kind>4</Kind>
    <Name>positionOffset.z</Name>
    <Value>-24.630554199</Value>
</Widget>
<Widget>
    <Kind>4</Kind>
    <Name>globalRotation.x</Name>
    <Value>-180.000000000</Value>
</Widget>
<Widget>
    <Kind>4</Kind>
    <Name>globalRotation.y</Name>
    <Value>0.886688232</Value>
</Widget>
<Widget>
    <Kind>4</Kind>
    <Name>globalRotation.z</Name>
    <Value>74.630615234</Value>
</Widget>
<Widget>
    <Kind>4</Kind>
    <Name>globalRotationVel.x</Name>
    <Value>0.197044373</Value>
</Widget>
<Widget>
    <Kind>4</Kind>
    <Name>globalRotationVel.y</Name>
    <Value>0.000000000</Value>
</Widget>
<Widget>
    <Kind>4</Kind>
    <Name>globalRotationVel.z</Name>
    <Value>0.000000000</Value>
</Widget>
