<Canvas>
    <Kind>42</Kind>
    <Name>Custom</Name>
    <IsMinified>0</IsMinified>
    <XPosition>1.000000000</XPosition>
    <YPosition>1.000000000</YPosition>
</Canvas>
<Widget>
    <Kind>2</Kind>
    <Name>Apply Force</Name>
    <Value>1</Value>
</Widget>
<Widget>
    <Kind>4</Kind>
    <Name>Force At Y</Name>
    <Value>4.546797752</Value>
</Widget>
<Widget>
    <Kind>4</Kind>
    <Name>Force Amount</Name>
    <Value>2.000000000</Value>
</Widget>
<Widget>
    <Kind>4</Kind>
    <Name>Particle Speed</Name>
    <Value>100.000000000</Value>
</Widget>
<Widget>
    <Kind>4</Kind>
    <Name>Particles Return</Name>
    <Value>0.049605913</Value>
</Widget>
<Widget>
    <Kind>2</Kind>
    <Name>Render Forces</Name>
    <Value>0</Value>
</Widget>
<Widget>
    <Kind>2</Kind>
    <Name>Render Particles</Name>
    <Value>1</Value>
</Widget>
<Widget>
    <Kind>4</Kind>
    <Name>Box Size</Name>
    <Value>1.942857265</Value>
</Widget>
<Widget>
    <Kind>2</Kind>
    <Name>Render Lines</Name>
    <Value>1</Value>
</Widget>
<Widget>
    <Kind>4</Kind>
    <Name>Box Connect Distance</Name>
    <Value>1.940886736</Value>
</Widget>
