<Canvas>
    <Kind>42</Kind>
    <Name>Presets</Name>
    <IsMinified>0</IsMinified>
    <XPosition>849.000122070</XPosition>
    <YPosition>1.000000000</YPosition>
</Canvas>
<Widget>
    <Kind>2</Kind>
    <Name>Agam</Name>
    <Value>0</Value>
</Widget>
<Widget>
    <Kind>2</Kind>
    <Name>Helix</Name>
    <Value>1</Value>
</Widget>
<Widget>
    <Kind>2</Kind>
    <Name>Helix-Inverted</Name>
    <Value>1</Value>
</Widget>
<Widget>
    <Kind>2</Kind>
    <Name>Progressive_Helix</Name>
    <Value>0</Value>
</Widget>
<Widget>
    <Kind>2</Kind>
    <Name>Progressive_wave_1</Name>
    <Value>1</Value>
</Widget>
<Widget>
    <Kind>2</Kind>
    <Name>Progressive_wormhole_1</Name>
    <Value>1</Value>
</Widget>
<Widget>
    <Kind>2</Kind>
    <Name>Treadmill</Name>
    <Value>0</Value>
</Widget>
<Widget>
    <Kind>2</Kind>
    <Name>Waerfront</Name>
    <Value>0</Value>
</Widget>
<Widget>
    <Kind>2</Kind>
    <Name>Waves</Name>
    <Value>0</Value>
</Widget>
<Widget>
    <Kind>2</Kind>
    <Name>Wormhole</Name>
    <Value>0</Value>
</Widget>
