<Canvas>
    <Kind>42</Kind>
    <Name>Presets</Name>
    <IsMinified>0</IsMinified>
    <XPosition>1185.000000000</XPosition>
    <YPosition>137.000000000</YPosition>
</Canvas>
<Widget>
    <Kind>2</Kind>
    <Name>aboveTheClouds</Name>
    <Value>0</Value>
</Widget>
<Widget>
    <Kind>2</Kind>
    <Name>bigNoise</Name>
    <Value>0</Value>
</Widget>
<Widget>
    <Kind>2</Kind>
    <Name>lewitt</Name>
    <Value>0</Value>
</Widget>
<Widget>
    <Kind>2</Kind>
    <Name>MC_cloudShadows</Name>
    <Value>0</Value>
</Widget>
<Widget>
    <Kind>2</Kind>
    <Name>MC_desert1</Name>
    <Value>0</Value>
</Widget>
<Widget>
    <Kind>2</Kind>
    <Name>MC_desert2</Name>
    <Value>0</Value>
</Widget>
<Widget>
    <Kind>2</Kind>
    <Name>MC_gloomy</Name>
    <Value>0</Value>
</Widget>
<Widget>
    <Kind>2</Kind>
    <Name>MC_infinite</Name>
    <Value>0</Value>
</Widget>
<Widget>
    <Kind>2</Kind>
    <Name>MC_shadow</Name>
    <Value>0</Value>
</Widget>
<Widget>
    <Kind>2</Kind>
    <Name>MC_shadows</Name>
    <Value>0</Value>
</Widget>
<Widget>
    <Kind>2</Kind>
    <Name>MC_wasteland</Name>
    <Value>0</Value>
</Widget>
<Widget>
    <Kind>2</Kind>
    <Name>mineCraft</Name>
    <Value>0</Value>
</Widget>
<Widget>
    <Kind>2</Kind>
    <Name>Minecraft2</Name>
    <Value>0</Value>
</Widget>
<Widget>
    <Kind>2</Kind>
    <Name>Minecraft3_wideangle</Name>
    <Value>0</Value>
</Widget>
<Widget>
    <Kind>2</Kind>
    <Name>NoiseAndScaling</Name>
    <Value>0</Value>
</Widget>
<Widget>
    <Kind>2</Kind>
    <Name>noiseFlow</Name>
    <Value>0</Value>
</Widget>
<Widget>
    <Kind>2</Kind>
    <Name>noiseScale</Name>
    <Value>0</Value>
</Widget>
<Widget>
    <Kind>2</Kind>
    <Name>MC_desert3</Name>
    <Value>0</Value>
</Widget>
<Widget>
    <Kind>2</Kind>
    <Name>MC_flyoverDesert</Name>
    <Value>0</Value>
</Widget>
<Widget>
    <Kind>2</Kind>
    <Name>MC_Burtynsky</Name>
    <Value>0</Value>
</Widget>
<Widget>
    <Kind>2</Kind>
    <Name>MC_infinite2</Name>
    <Value>0</Value>
</Widget>
<Widget>
    <Kind>2</Kind>
    <Name>MC_shadows2</Name>
    <Value>0</Value>
</Widget>
<Widget>
    <Kind>2</Kind>
    <Name>MC_airplane1</Name>
    <Value>0</Value>
</Widget>
<Widget>
    <Kind>2</Kind>
    <Name>bigNoise2</Name>
    <Value>0</Value>
</Widget>
<Widget>
    <Kind>2</Kind>
    <Name>BigNoiseBW</Name>
    <Value>0</Value>
</Widget>
<Widget>
    <Kind>2</Kind>
    <Name>noiseFlow2</Name>
    <Value>1</Value>
</Widget>
