<credits>
	
	<!-- US -->
	<credit align="center">
		<title>
			DIRECTORS
		</title>
		<name>
			Jonathan Minard, James George
		</name>
	</credit>
	
	<!-- GOLAN -->
	<credit align="right">
		<title>
			EXECUTIVE PRODUCER
		</title>
		<name>
			Golan Levin 
		</name>
	</credit>

	<!-- WINSLOW -->
	<credit align="left">
		<title>
			PRODUCER
		</title>
		<name>
			Winslow Porter
		</name>
	</credit>

	<!-- LUKE -->
	<credit align="left">
		<title>
			MUSIC
		</title>
		<name>
			R. Luke DuBois
		</name>
	</credit>

	<!-- BRADLEY -->
	<credit align="left">
		<title>
			DESIGN DIRECTOR
		</title>
		<name>
			Bradley GMUNK Munkowitz
		</name>
	</credit>

	<!-- ELIE -->
	<credit align="left">
		<title>
			INTERACTION PROGRAMMING
		</title>
		<name>
			Elie Zananiri
		</name>
	</credit>
	
	<!-- LARS -->
	<credit align="right">
		<title>
			LEAD VISUAL PROGRAMMING
		</title>
		<name>
			Lars Berg
		</name>
	</credit>
	
	<!-- SURYA -->
	<credit align="left">
		<title>
			LEAD NARRATIVE PROGRAMMING
		</title>
		<name>
			Surya A. Mattu
		</name>
	</credit>


<credit align="left">
		<title>
			Casey Reas
		</title>
		<name>

			Bruce Sterling

		</name>
	</credit>

<credit align="left">
		<title>
			Daniel Shiffman
		</title>
		<name>
			

			Diederick Huijbers

		</name>
	</credit>


<credit align="left">
		<title>
			Elliot Woods
			
		</title>
		<name>


			Golan Levin

	</name>

	</credit>
	<credit align="left">
		<title>
			Greg Borenstein
			
		</title>
		<name>

			Jer Thorp
		</name>
	</credit>

	<credit align="left">
		<title>
			Jesse Louis-Rosenberg
		</title>
		<name>
			Jessica Rosenkrantz

		</name>
	</credit>

	<credit align="left">
		<title>

			Joel Gethin Lewis
			
		</title>
		<name>

			John Maeda

	</name>
	</credit>
	
	<credit align="left">
		<title>
			Josh Nimoy
		</title>
		<name>

			Julia Kaganskiy
		</name>
	</credit>

	<credit align="left">
		<title>
			Julian Oliver
			
		</title>
		<name>

			Karolina Sobecka

		</name>
	</credit>

	<credit align="left">
		<title>
			Karsten Schmidt			
		</title>
		<name>

			Kyle Chayka
			</name>
	</credit>

	<credit align="left">
		<title>
			Kyle McDonald			
		</title>
		<name>

			Lindsay Howard

			</name>
	</credit>

	<credit align="left">
		<title>
			Marcus Wendt			
		</title>
		<name>

			Marius Watz

		</name>
	</credit>

		<credit align="left">
		<title>
			Nick Fox-Gieg
			
		</title>
		<name>


			Philip Whitfield

		</name>
	</credit>

			
	<credit align="left">
		<title>
			Rachel Binx			
		</title>
		<name>

			Regine Debatty
		</name>
	</credit>


	<credit align="left">
		<title>
			Satoru Higa			
		</title>
		<name>

			Shantell Martin

		</name>
	</credit>


	<credit align="left">
		<title>
			Sofy Yuditskaya
		</title>
		<name>
			

			Theodore Watson

		</name>
	</credit>

		<credit align="left">
		<title>
			Vera Glahn			
		</title>
		<name>

			Zachary Lieberman
		</name>
	</credit>
	

<!-- Creative Coders -->

	<credit align="left">
		<title>
			CREATIVE DEVELOPERS
		</title>
		<name>
			Lars Berg 
			Patricio González-Vivo

		</name>
	</credit>


	<credit align="left">
		<title>
			CREATIVE DEVELOPERS
		</title>
		<name>

			Jeff Crouse

			Gal Sasson


		</name>
	</credit>

	<credit align="left">
		<title>
			CREATIVE DEVELOPERS
		</title>
		<name>

			Neil Mendoza

			Omer Shapira

	</name>
	</credit>

	<credit align="left">
		<title>
			CREATIVE DEVELOPERS
		</title>
		<name>

			Reza Ali

			Michael Allison

		</name>
	</credit>

	

	<credit align="left">
		<title>
			INTERFACE DESIGN
		</title>
		<name>

			Luisa Pereira

			Sarah Hallacher
		</name>
	</credit>

	<credit align="left">
		<title>
			INTERFACE DESIGN
		</title>
		<name>

			Charlie Whitney

			Jack Kailash

		</name>
	</credit>

	<credit align="left">
		<title>
			SECOND CAMERA
		</title>
		<name>

			Alexander Porter

		</name>
	</credit>

	<credit align="left">
		<title>
			LIGHTING
		</title>
		<name>

			Paul Porter

		</name>
	</credit>

	<credit align="left">
		<title>
			ADDITIONAL FOOTAGE
		</title>
		<name>

			Matt Rutherford

		</name>
	</credit>
	
	<credit align="left">
		<title>
			ADDITIONAL SOUND
		</title>
		<name>
			Jules Laplace
		</name>
	</credit>
	

	<credit align="left">
		<title>
			SOUND ENGINEER
		</title>
		<name>
			Brett Murphy
		</name>
	</credit>


	<credit align="left">
		<title>
			SPONSORS
		</title>
		<name>
			Studio for Creative Inquiry
		</name>
	</credit>

	<credit align="left">
		<title>
			SPONSORS
		</title>
		<name>
			Eyebeam Art and Technology Center
		</name>
	</credit>

	<credit align="left">
		<title>
			SPONSORS
		</title>
		<name>
			Microsoft Research
		</name>
	</credit>

	<credit align="left">
		<title>
			MADE WITH
		</title>
		<name>
			openFrameworks
		</name>
	</credit>


	<credit align="left">
		<title>
			THANK YOU 
		</title>
		<name>
			Kickstarter Backers
		</name>
	</credit>



	
</credits>
<!--
Executive Producer: Golan Levin 

Producer: Winslow Porter

Music Composer: Luke DuBois Design Director: Bradley G 

Munkowitz

Interaction Developer: Elie Zananiri

System Engineer: Surya Mattu

Interface Design: Sarah Hallacher, 

Erica Gorochow

Additional Programming: Lars Berg, 

Patricio González-Vivo, Luisa 

Pereira, Jeff Crouse, Gal Sasson, 

Neil Mendoza, Omer Shapira, 

Reza Ali, Michael Allison, Charlie 

Whitney, Jack Kalish, Jason 

Walters

Additional Sound: Jules Laplace

Sound Engineer: Brett Murphy
-->