<Canvas>
    <Kind>42</Kind>
    <Name>Surface</Name>
    <IsMinified>0</IsMinified>
    <XPosition>1</XPosition>
    <YPosition>44</YPosition>
</Canvas>
<Widget>
    <Kind>2</Kind>
    <Name>draw surface</Name>
    <Value>0</Value>
</Widget>
<Widget>
    <Kind>2</Kind>
    <Name>smooth surface</Name>
    <Value>1</Value>
</Widget>
<Widget>
    <Kind>4</Kind>
    <Name>noiseScale</Name>
    <Value>0.00797389</Value>
</Widget>
<Widget>
    <Kind>4</Kind>
    <Name>noiseOffset</Name>
    <Value>0</Value>
</Widget>
<Widget>
    <Kind>4</Kind>
    <Name>noiseTimeScale</Name>
    <Value>2</Value>
</Widget>
