<keyframes>
    <key>
        <easefunc>0</easefunc>
        <easetype>0</easetype>
        <time>00:00:00:296</time>
        <value>0.050000012</value>
    </key>
    <key>
        <easefunc>0</easefunc>
        <easetype>0</easetype>
        <time>00:00:14:013</time>
        <value>0.111111104</value>
    </key>
    <key>
        <easefunc>0</easefunc>
        <easetype>0</easetype>
        <time>00:00:22:796</time>
        <value>0.574999988</value>
    </key>
    <key>
        <easefunc>0</easefunc>
        <easetype>0</easetype>
        <time>00:00:23:433</time>
        <value>0.100000024</value>
    </key>
    <key>
        <easefunc>0</easefunc>
        <easetype>0</easetype>
        <time>00:00:31:430</time>
        <value>0.074999988</value>
    </key>
    <key>
        <easefunc>0</easefunc>
        <easetype>0</easetype>
        <time>00:00:40:521</time>
        <value>0.125000000</value>
    </key>
    <key>
        <easefunc>0</easefunc>
        <easetype>0</easetype>
        <time>00:00:52:141</time>
        <value>0.449999988</value>
    </key>
    <key>
        <easefunc>0</easefunc>
        <easetype>0</easetype>
        <time>00:01:00:000</time>
        <value>1.000000000</value>
    </key>
</keyframes>
