<keyframes>
    <key>
        <px>406.404754639</px>
        <py>-7.237748146</py>
        <pz>86.412178040</pz>
        <ox>0.920178771</ox>
        <oy>-0.078343332</oy>
        <oz>0.354817182</oz>
        <ow>0.145738915</ow>
        <easein>0</easein>
        <easeout>0</easeout>
        <time>00:00:00:000</time>
        <value>0.000000000</value>
    </key>
    <key>
        <px>865.979553223</px>
        <py>-310.784851074</py>
        <pz>217.387542725</pz>
        <ox>0.830275774</ox>
        <oy>-0.152550742</oy>
        <oz>0.363528937</oz>
        <ow>0.393976092</ow>
        <easein>0</easein>
        <easeout>0</easeout>
        <time>00:00:29:966</time>
        <value>0.000000000</value>
    </key>
    <key>
        <px>637.940185547</px>
        <py>-33.249874115</py>
        <pz>535.404724121</pz>
        <ox>0.704294622</ox>
        <oy>-0.139214069</oy>
        <oz>0.680955946</oz>
        <ow>0.144525379</ow>
        <easein>0</easein>
        <easeout>0</easeout>
        <time>00:01:03:337</time>
        <value>0.000000000</value>
    </key>
    <key>
        <px>575.207946777</px>
        <py>-2.157082796</py>
        <pz>561.638671875</pz>
        <ox>0.713401437</ox>
        <oy>-0.066343397</oy>
        <oz>0.694130838</oz>
        <ow>0.069534838</ow>
        <easein>0</easein>
        <easeout>0</easeout>
        <time>00:01:32:943</time>
        <value>0.199999988</value>
    </key>
</keyframes>
