<keyframes>
    <key>
        <easefunc>0</easefunc>
        <easetype>0</easetype>
        <time>00:00:04:649</time>
        <value>0.524999976</value>
    </key>
    <key>
        <easefunc>0</easefunc>
        <easetype>0</easetype>
        <time>00:00:10:373</time>
        <value>0.550000012</value>
    </key>
    <key>
        <easefunc>0</easefunc>
        <easetype>0</easetype>
        <time>00:00:12:655</time>
        <value>0.199999988</value>
    </key>
    <key>
        <easefunc>0</easefunc>
        <easetype>0</easetype>
        <time>00:00:17:114</time>
        <value>0.300000012</value>
    </key>
    <key>
        <easefunc>0</easefunc>
        <easetype>0</easetype>
        <time>00:00:35:265</time>
        <value>0.149999976</value>
    </key>
</keyframes>
