<Canvas>
    <Kind>42</Kind>
    <Name>PhotoGlitch</Name>
    <IsMinified>0</IsMinified>
    <XPosition>1.000000000</XPosition>
    <YPosition>1.000000000</YPosition>
</Canvas>
<Widget>
    <Kind>44</Kind>
    <Name>DELAY B/W TWEENS</Name>
    <Value>1</Value>
</Widget>
<Widget>
    <Kind>44</Kind>
    <Name>NUM COLS</Name>
    <Value>63</Value>
</Widget>
<Widget>
    <Kind>44</Kind>
    <Name>NUM ROWS</Name>
    <Value>61</Value>
</Widget>
<Widget>
    <Kind>2</Kind>
    <Name>USE COLORS</Name>
    <Value>1</Value>
</Widget>
<Widget>
    <Kind>2</Kind>
    <Name>USE TEXTURE</Name>
    <Value>1</Value>
</Widget>
<Widget>
    <Kind>2</Kind>
    <Name>DRAW TARGET</Name>
    <Value>0</Value>
</Widget>
<Widget>
    <Kind>2</Kind>
    <Name>DRAW BACKGROUND</Name>
    <Value>0</Value>
</Widget>
<Widget>
    <Kind>44</Kind>
    <Name>TWEEN DURATION</Name>
    <Value>1000</Value>
</Widget>
<Widget>
    <Kind>44</Kind>
    <Name>TWEEN DELAY</Name>
    <Value>1</Value>
</Widget>
<Widget>
    <Kind>2</Kind>
    <Name>PERPENDICULAR</Name>
    <Value>1</Value>
</Widget>
<Widget>
    <Kind>2</Kind>
    <Name>ANIMATE SOURCE</Name>
    <Value>0</Value>
</Widget>
<Widget>
    <Kind>2</Kind>
    <Name>SOURCE SHUFFLE</Name>
    <Value>0</Value>
</Widget>
<Widget>
    <Kind>2</Kind>
    <Name>SOURCE SORT HUE</Name>
    <Value>0</Value>
</Widget>
<Widget>
    <Kind>2</Kind>
    <Name>SOURCE SORT BRI</Name>
    <Value>0</Value>
</Widget>
<Widget>
    <Kind>2</Kind>
    <Name>SOURCE REORDER</Name>
    <Value>1</Value>
</Widget>
<Widget>
    <Kind>2</Kind>
    <Name>LOOP BACK TO SOURCE</Name>
    <Value>1</Value>
</Widget>
<Widget>
    <Kind>17</Kind>
    <Name>Cells.jpg</Name>
    <Value>0</Value>
</Widget>
<Widget>
    <Kind>17</Kind>
    <Name>Cells_cooler.jpg</Name>
    <Value>0</Value>
</Widget>
<Widget>
    <Kind>17</Kind>
    <Name>Cells_milder.jpg</Name>
    <Value>0</Value>
</Widget>
<Widget>
    <Kind>17</Kind>
    <Name>Cells_warmer.jpg</Name>
    <Value>0</Value>
</Widget>
<Widget>
    <Kind>17</Kind>
    <Name>Desktops.jpg</Name>
    <Value>0</Value>
</Widget>
<Widget>
    <Kind>17</Kind>
    <Name>Glitch_Compiled.jpg</Name>
    <Value>1</Value>
</Widget>
<Widget>
    <Kind>17</Kind>
    <Name>People.jpg</Name>
    <Value>0</Value>
</Widget>
<Widget>
    <Kind>17</Kind>
    <Name>PeopleComposit.jpg</Name>
    <Value>0</Value>
</Widget>
<Widget>
    <Kind>17</Kind>
    <Name>Whitney.jpg</Name>
    <Value>0</Value>
</Widget>
<Widget>
    <Kind>17</Kind>
    <Name>browser.png</Name>
    <Value>0</Value>
</Widget>
<Widget>
    <Kind>17</Kind>
    <Name>catglitch.jpg</Name>
    <Value>0</Value>
</Widget>
<Widget>
    <Kind>17</Kind>
    <Name>desktop.png</Name>
    <Value>0</Value>
</Widget>
<Widget>
    <Kind>17</Kind>
    <Name>dogs.jpg</Name>
    <Value>0</Value>
</Widget>
<Widget>
    <Kind>17</Kind>
    <Name>friends.jpg</Name>
    <Value>0</Value>
</Widget>
<Widget>
    <Kind>17</Kind>
    <Name>glitch.jpg</Name>
    <Value>0</Value>
</Widget>
<Widget>
    <Kind>17</Kind>
    <Name>glitch2.jpeg</Name>
    <Value>0</Value>
</Widget>
<Widget>
    <Kind>17</Kind>
    <Name>sexy-desktop.jpg</Name>
    <Value>0</Value>
</Widget>
<Widget>
    <Kind>17</Kind>
    <Name>sunset.jpg</Name>
    <Value>0</Value>
</Widget>
<Widget>
    <Kind>17</Kind>
    <Name>tiles.jpg</Name>
    <Value>0</Value>
</Widget>
