<keyframes>
    <key>
        <px>200.440994263</px>
        <py>1.034649968</py>
        <pz>159.600006104</pz>
        <ox>0.306973994</ox>
        <oy>0.307116002</oy>
        <oz>0.640097022</oz>
        <ow>0.633822024</ow>
        <easein>0</easein>
        <easeout>0</easeout>
        <time>00:00:00:000</time>
        <value>0.667273998</value>
    </key>
    <key>
        <px>13.243000031</px>
        <py>-16.788099289</py>
        <pz>255.328002930</pz>
        <ox>0.041491602</ox>
        <oy>-0.004772890</oy>
        <oz>0.704378009</oz>
        <ow>0.708603024</ow>
        <easein>0</easein>
        <easeout>0</easeout>
        <time>00:00:15:143</time>
        <value>0.667273998</value>
    </key>
    <key>
        <px>-108.281997681</px>
        <py>148.880996704</py>
        <pz>178.210998535</pz>
        <ox>-0.143305004</ox>
        <oy>0.362904012</oy>
        <oz>0.891501009</oz>
        <ow>-0.230228007</ow>
        <easein>0</easein>
        <easeout>0</easeout>
        <time>00:00:24:545</time>
        <value>0.667273998</value>
    </key>
</keyframes>
