<Canvas>
    <Kind>42</Kind>
    <Name>Mesh</Name>
    <IsMinified>0</IsMinified>
    <XPosition>895.000000000</XPosition>
    <YPosition>524.000000000</YPosition>
</Canvas>
<Widget>
    <Kind>2</Kind>
    <Name>ENABLE</Name>
    <Value>1</Value>
</Widget>
<Widget>
    <Kind>4</Kind>
    <Name>Mesh Alpha</Name>
    <Value>0.699507415</Value>
</Widget>
<Widget>
    <Kind>4</Kind>
    <Name>X Simplify</Name>
    <Value>4.029556751</Value>
</Widget>
<Widget>
    <Kind>4</Kind>
    <Name>Y Simplify</Name>
    <Value>2.773398876</Value>
</Widget>
<Widget>
    <Kind>4</Kind>
    <Name>Random Variance</Name>
    <Value>1.921182275</Value>
</Widget>
<Widget>
    <Kind>4</Kind>
    <Name>Face Min Radius</Name>
    <Value>141.871917725</Value>
</Widget>
<Widget>
    <Kind>4</Kind>
    <Name>Face Falloff</Name>
    <Value>466.995086670</Value>
</Widget>
<Widget>
    <Kind>4</Kind>
    <Name>Edge Geo Retraction</Name>
    <Value>0.798029542</Value>
</Widget>
