<Canvas>
    <Kind>42</Kind>
    <Name>Animation</Name>
    <IsMinified>0</IsMinified>
    <XPosition>1.000000000</XPosition>
    <YPosition>476.000000000</YPosition>
</Canvas>
<Widget>
    <Kind>4</Kind>
    <Name>START TIME RANGE</Name>
    <Value>0.669950724</Value>
</Widget>
<Widget>
    <Kind>6</Kind>
    <Name>EXPAND SPEED RANGE</Name>
    <HighValue>0.866995096</HighValue>
    <LowValue>0.500000000</LowValue>
</Widget>
<Widget>
    <Kind>6</Kind>
    <Name>SPEED RANGE</Name>
    <HighValue>0.868325114</HighValue>
    <LowValue>0.468423635</LowValue>
</Widget>
<Widget>
    <Kind>4</Kind>
    <Name>10PRINT SPEED</Name>
    <Value>20.000000000</Value>
</Widget>
<Widget>
    <Kind>2</Kind>
    <Name>CASCADE</Name>
    <Value>0</Value>
</Widget>
