<Canvas>
    <Kind>42</Kind>
    <Name>LOOKS</Name>
    <IsMinified>0</IsMinified>
    <XPosition>849.000061035</XPosition>
    <YPosition>1.000000000</YPosition>
</Canvas>
<Widget>
    <Kind>2</Kind>
    <Name>Level Set BG</Name>
    <Value>1</Value>
</Widget>
<Widget>
    <Kind>4</Kind>
    <Name>Level Set Shadow</Name>
    <Value>0.500000000</Value>
</Widget>
<Widget>
    <Kind>4</Kind>
    <Name>Cell Floor Translusence</Name>
    <Value>0.266009539</Value>
</Widget>
<Widget>
    <Kind>4</Kind>
    <Name>Dish Floor Translusence</Name>
    <Value>0.251231223</Value>
</Widget>
<Widget>
    <Kind>5</Kind>
    <Name>R</Name>
    <Value>0.562500000</Value>
</Widget>
<Widget>
    <Kind>5</Kind>
    <Name>G</Name>
    <Value>0.000000000</Value>
</Widget>
<Widget>
    <Kind>5</Kind>
    <Name>B</Name>
    <Value>0.712499976</Value>
</Widget>
<Widget>
    <Kind>5</Kind>
    <Name>A</Name>
    <Value>0.000000000</Value>
</Widget>
<Widget>
    <Kind>4</Kind>
    <Name>Stipple Scale</Name>
    <Value>0.147782654</Value>
</Widget>
<Widget>
    <Kind>5</Kind>
    <Name>R1</Name>
    <Value>0.137499988</Value>
</Widget>
<Widget>
    <Kind>5</Kind>
    <Name>G1</Name>
    <Value>1.000000000</Value>
</Widget>
<Widget>
    <Kind>5</Kind>
    <Name>B1</Name>
    <Value>0.712499976</Value>
</Widget>
<Widget>
    <Kind>5</Kind>
    <Name>A1</Name>
    <Value>1.000000000</Value>
</Widget>
<Widget>
    <Kind>5</Kind>
    <Name>R2</Name>
    <Value>0.824999988</Value>
</Widget>
<Widget>
    <Kind>5</Kind>
    <Name>G2</Name>
    <Value>1.000000000</Value>
</Widget>
<Widget>
    <Kind>5</Kind>
    <Name>B2</Name>
    <Value>0.337499976</Value>
</Widget>
<Widget>
    <Kind>5</Kind>
    <Name>A2</Name>
    <Value>1.000000000</Value>
</Widget>
<Widget>
    <Kind>4</Kind>
    <Name>Shadow</Name>
    <Value>0.500000000</Value>
</Widget>
<Widget>
    <Kind>17</Kind>
    <Name>blur_square3.jpg</Name>
    <Value>0</Value>
</Widget>
<Widget>
    <Kind>17</Kind>
    <Name>darkpointy_square.png</Name>
    <Value>1</Value>
</Widget>
<Widget>
    <Kind>17</Kind>
    <Name>dirt.jpg</Name>
    <Value>0</Value>
</Widget>
<Widget>
    <Kind>17</Kind>
    <Name>dirt2.jpg</Name>
    <Value>0</Value>
</Widget>
<Widget>
    <Kind>17</Kind>
    <Name>dirt_square.jpg</Name>
    <Value>0</Value>
</Widget>
<Widget>
    <Kind>17</Kind>
    <Name>grime_square.png</Name>
    <Value>0</Value>
</Widget>
<Widget>
    <Kind>17</Kind>
    <Name>pointy_square.png</Name>
    <Value>0</Value>
</Widget>
