<keyframes>
    <key>
        <easefunc>0</easefunc>
        <easetype>0</easetype>
        <time>00:00:01:637</time>
        <value>0.399999976</value>
    </key>
    <key>
        <easefunc>0</easefunc>
        <easetype>0</easetype>
        <time>00:00:07:598</time>
        <value>0.625000000</value>
    </key>
    <key>
        <easefunc>0</easefunc>
        <easetype>0</easetype>
        <time>00:00:13:147</time>
        <value>0.375000000</value>
    </key>
    <key>
        <easefunc>0</easefunc>
        <easetype>0</easetype>
        <time>00:00:19:324</time>
        <value>0.649999976</value>
    </key>
    <key>
        <easefunc>0</easefunc>
        <easetype>0</easetype>
        <time>00:00:26:619</time>
        <value>0.399999976</value>
    </key>
    <key>
        <easefunc>0</easefunc>
        <easetype>0</easetype>
        <time>00:00:36:050</time>
        <value>0.625000000</value>
    </key>
    <key>
        <easefunc>0</easefunc>
        <easetype>0</easetype>
        <time>00:00:46:185</time>
        <value>0.399999976</value>
    </key>
</keyframes>
